LICENSE
MANIFEST.in
README.md
setup.py
singularity/__init__.py
singularity/utils.py
singularity/version.py
singularity.egg-info/PKG-INFO
singularity.egg-info/SOURCES.txt
singularity.egg-info/dependency_links.txt
singularity.egg-info/not-zip-safe
singularity.egg-info/requires.txt
singularity.egg-info/top_level.txt
singularity/analysis/__init__.py
singularity/analysis/apps.py
singularity/analysis/classify.py
singularity/analysis/compare.py
singularity/analysis/metrics.py
singularity/analysis/utils.py
singularity/analysis/reproduce/__init__.py
singularity/analysis/reproduce/criteria.py
singularity/analysis/reproduce/hash.py
singularity/analysis/reproduce/levels.py
singularity/analysis/reproduce/metrics.py
singularity/analysis/reproduce/utils.py
singularity/analysis/reproduce/data/__init__.py
singularity/analysis/reproduce/data/reproduce_levels.json
singularity/analysis/reproduce/data/reproduce_levels_2-2.json
singularity/analysis/reproduce/data/reproduce_levels_2-3.json
singularity/build/__init__.py
singularity/build/auth.py
singularity/build/main.py
singularity/build/utils.py
singularity/build/google/__init__.py
singularity/build/google/instances.py
singularity/build/google/storage.py
singularity/build/google/utils.py
singularity/build/scripts/singularity-build-2.3.sh
singularity/build/scripts/singularity-build-dev.sh
singularity/build/scripts/singularity-build-latest.sh
singularity/build/scripts/singularity-prepare-instance.sh
singularity/logger/__init__.py
singularity/logger/message.py
singularity/logger/progress.py
singularity/logger/spinner.py
singularity/package/__init__.py
singularity/package/clone.py
singularity/package/utils.py
singularity/tests/__init__.py
singularity/tests/run_tests.sh
singularity/tests/test_analysis_compare.py
singularity/tests/test_build.py
singularity/tests/test_build_utils.py
singularity/tests/test_reproduce.py
singularity/tests/test_utils.py
singularity/views/__init__.py
singularity/views/trees.py
singularity/views/utils.py